rich_msa/__init__.py
rich_msa/__main__.py
rich_msa/cli.py
rich_msa/py.typed
rich_msa-0.1.0.dist-info/COPYING
rich_msa-0.1.0.dist-info/METADATA
rich_msa-0.1.0.dist-info/WHEEL
rich_msa-0.1.0.dist-info/top_level.txt
rich_msa-0.1.0.dist-info/zip-safe
rich_msa-0.1.0.dist-info/RECORD
