Metadata-Version: 2.1
Name: rich-msa
Version: 0.1.0
Summary: A Rich renderable for viewing Multiple Sequence Alignments in the terminal.
Home-page: https://github.com/althonos/rich-msa
Author: Martin Larralde
Author-email: martin.larralde@embl.de
License: MIT
Project-URL: Bug Tracker, https://github.com/althonos/rich-msa/issues
Project-URL: Changelog, https://github.com/althonos/rich-msa/blob/master/CHANGELOG.md
Project-URL: Builds, https://git.embl.de/larralde/rich-msa/-/pipelines
Project-URL: PyPI, https://pypi.org/project/rich-msa
Keywords: bioinformatics,protein,alignment,viewer,domains
Platform: posix
Classifier: Development Status :: 4 - Beta
Classifier: Intended Audience :: Developers
Classifier: Intended Audience :: Science/Research
Classifier: License :: OSI Approved :: MIT License
Classifier: Operating System :: OS Independent
Classifier: Programming Language :: C
Classifier: Programming Language :: Cython
Classifier: Programming Language :: Python :: 3.6
Classifier: Programming Language :: Python :: 3.7
Classifier: Programming Language :: Python :: 3.8
Classifier: Programming Language :: Python :: 3.9
Classifier: Programming Language :: Python :: 3.10
Classifier: Programming Language :: Python :: Implementation :: CPython
Classifier: Programming Language :: Python :: Implementation :: PyPy
Classifier: Topic :: Scientific/Engineering :: Bio-Informatics
Classifier: Topic :: Scientific/Engineering :: Medical Science Apps.
Classifier: Typing :: Typed
Requires-Python: >=3.6
License-File: COPYING
Requires-Dist: rich
